geom_archetypal/__init__.py
geom_archetypal/geom_archetypal.py
geom_archetypal-1.0.2.dist-info/LICENSE
geom_archetypal-1.0.2.dist-info/METADATA
geom_archetypal-1.0.2.dist-info/WHEEL
geom_archetypal-1.0.2.dist-info/top_level.txt
geom_archetypal-1.0.2.dist-info/RECORD
