Metadata-Version: 2.1
Name: geom_archetypal
Version: 1.0.2
Summary: Geometric Archetypal Analysis
Author-email: Demetris Christopoulos <dchristop@econ.uoa.gr>
Maintainer-email: Demetris Christopoulos <dchristop@econ.uoa.gr>
License: Copyright (c) 2024 Demetris Christopoulos
Project-URL: Homepage, https://github.com/dchristop/geom_archetypal
Project-URL: Issues, https://github.com/dchristop/geom_archetypal/issues
Project-URL: Funding, https://www.insead.edu/hoffmann-institute
Keywords: geometrical archetypal analysis,convex hull,grid archetypal
Classifier: Programming Language :: Python :: 3
Classifier: License :: OSI Approved :: MIT License
Classifier: Operating System :: OS Independent
Requires-Python: >=3.8
License-File: LICENSE
